MIPS32_RISC.v
// *** MIPS32 PROCESSOR USING 5-STAGE PIPELINING RISC-V 

module MIPS_32 (clk1,clk2) ;

input clk1,clk2 ; // Two phase non-overlapping clock

reg [31:0] PC , IF_ID_IR , IF_ID_NPC ;    // IF_ID pipeline latch
reg [31:0] ID_EX_NPC , ID_EX_A , ID_EX_B , ID_EX_Imm , ID_EX_IR ; // ID_EX pipeline latch
reg [2:0] ID_EX_type , EX_MEM_type , MEM_WB_type ;
reg [31:0] EX_MEM_cond , EX_MEM_ALUout , EX_MEM_B , EX_MEM_IR ; // EX_MEM pipeline latch 
reg [31:0] MEM_WB_LMD , MEM_WB_ALUout , MEM_WB_IR ;  // MEM_WB pipeline latch

reg [31:0] Reg [0:31] ;  // Register Bank [ 32 registers X 32 bits ]
reg [31:0] Mem [0:1023] ; // Memory [ 1024 words X 32 bits ]

parameter ADD=6'b000000 , SUB=6'b000001 , AND=6'b000010 , OR=6'b000011 , SLT=6'b000100 , MUL=6'b000101 , // Arithemetic and Logical Instructions
          HLT=6'b111111 , // Halt Instruction 
          LW=6'b001000 , SW=6'b001001 , // Load and Store Instructions
          ADDI=6'b001010 , SUBI=6'b001011 , SLTI=6'b001100 , // Immediate Instructions
          BNEQZ=6'b001101 , BEQZ=6'b001110 ;  // Branch Instructions

parameter RR_ALU=3'b000 , RM_ALU=3'b001 , LOAD=3'b010 , 
          STORE=3'b011 , BRANCH=3'b100 , HALT=3'b101 ;          
          
reg HALTED ; // Set after HLT instruction is completed ( in WB stage ) 
reg TAKEN_BRANCH ;  // Required to disable instructions after branch

wire [4:0] rs,rt ; // rs --> Source Register 1 (rs <- IR[25:21]) || rt --> Source Register 2 (rt <- IR[20:16])
wire [5:0] op_code ;  // op_code <-- IR[31:26]
wire [15:0] immediate ;  // immediate <-- IR[15:0]

assign op_code = IF_ID_IR[31:26] ;
assign rs = IF_ID_IR[25:21] ;
assign rt = IF_ID_IR[20:16] ;
assign immediate = IF_ID_IR[15:0] ;


// ***** IF STAGE *****
always @ (posedge clk1) 
    
    if ( HALTED==0 )
            begin
                if ( ( (EX_MEM_IR[31:26] == BEQZ) && (EX_MEM_cond == 1) ) || 
                     ( (EX_MEM_IR[31:26] == BNEQZ) && (EX_MEM_cond == 0) ) )   // FOR BRANCH INSTRUCTIONS

                    begin
                        IF_ID_IR <= #2 Mem[EX_MEM_ALUout] ;
                        TAKEN_BRANCH <= #2 1'b1 ;
                        IF_ID_NPC <= #2 EX_MEM_ALUout ;
                        PC <= #2 EX_MEM_ALUout ;
                    end

                else
                    begin                            // FOR NORMAL ARITHMETIC AND LOGIC INSTRUCTIONS
                        IF_ID_IR <= #2 Mem[PC] ;
                        IF_ID_NPC <= #2 PC+1 ;
                        PC <= #2 PC+1 ;
                    end    

            end

// ***** ID STAGE ***** 
always @ (posedge clk2)

    if (HALTED==0)
        begin
            case (op_code)   // Operation_Code
                ADD,SUB,MUL,AND,OR,SLT : ID_EX_type <= #2 RR_ALU ;
                ADDI,SUBI,SLTI : ID_EX_type <= #2 RM_ALU ;
                LW : ID_EX_type <= #2 LOAD ;
                SW : ID_EX_type <= #2 STORE ;
                BNEQZ,BEQZ : ID_EX_type <= #2 BRANCH ;
                HLT : ID_EX_type <= #2 HALT ;

                default : ID_EX_type <= #2 HALT ; // invalid op_code
            endcase

            if ( rs == 5'b00000 ) ID_EX_A <= #2 0 ;
            else ID_EX_A <= #2 Reg[rs] ;   // Source Register 1

            if ( rt == 5'b00000 ) ID_EX_B <= #2 0 ;
            else ID_EX_B <= #2 Reg[rt] ;   // Source Register 2

            ID_EX_Imm <= #2 {{16{immediate[15]}}, immediate} ;  // Sign extension

            ID_EX_IR <= #2 IF_ID_IR ;
            ID_EX_NPC <= #2 IF_ID_NPC ;
        end

// ***** EX STAGE *****
always @ (posedge clk1)

    if ( HALTED==0 )
        begin
            EX_MEM_IR <= #2 ID_EX_IR ;
            EX_MEM_type <= #2 ID_EX_type ;
            TAKEN_BRANCH <= #2 1'b0 ; // Reset the "TAKEN_BRANCH"

            case (ID_EX_type)

            RR_ALU : begin  
                        case (ID_EX_IR[31:26])  // opcode
                        ADD : EX_MEM_ALUout <= #2 ID_EX_A + ID_EX_B ;
                        SUB : EX_MEM_ALUout <= #2 ID_EX_A - ID_EX_B ;
                        MUL : EX_MEM_ALUout <= #2 ID_EX_A * ID_EX_B ;
                        AND : EX_MEM_ALUout <= #2 ID_EX_A & ID_EX_B ;
                        OR  : EX_MEM_ALUout <= #2 ID_EX_A | ID_EX_B ;
                        SLT : EX_MEM_ALUout <= #2 ID_EX_A < ID_EX_B ;
                        default :EX_MEM_ALUout <= #2 32'hxxxxxxxx ;
                        endcase
                     end

            RM_ALU : begin 
                        case (ID_EX_IR[31:26]) // opcode
                        ADDI : EX_MEM_ALUout <= #2 ID_EX_A + ID_EX_Imm ;
                        SUBI : EX_MEM_ALUout <= #2 ID_EX_A - ID_EX_Imm ;
                        SLTI : EX_MEM_ALUout <= #2 ID_EX_A < ID_EX_Imm ;
                        default :EX_MEM_ALUout <= #2 32'hxxxxxxxx ;
                        endcase
                     end     

            LOAD,STORE :begin   
                            EX_MEM_ALUout <= #2 ID_EX_A + ID_EX_Imm ;
                            EX_MEM_B <= #2 ID_EX_B ;   // required for store instructions
                        end       

            BRANCH : begin
                        EX_MEM_ALUout <= #2 ID_EX_NPC + ID_EX_Imm ;
                        EX_MEM_cond <= #2 (ID_EX_A == 0) ;
                     end         

            endcase 
        end

// ***** MEM STAGE *****
always @ (posedge clk2)

    if ( HALTED == 0 )
        begin
            MEM_WB_IR <= #2 EX_MEM_IR ;
            MEM_WB_type <= #2 EX_MEM_type ;

            case (EX_MEM_type)
            RR_ALU,RM_ALU : MEM_WB_ALUout <= #2 EX_MEM_ALUout ;

            LOAD : MEM_WB_LMD <= #2 Mem[EX_MEM_ALUout] ;

            STORE : if ( TAKEN_BRANCH == 0 )
                        Mem[EX_MEM_ALUout] <= #2 EX_MEM_B ;
            endcase
        end

// ***** WB STAGE *****
always @(posedge clk1)

        begin
            if ( TAKEN_BRANCH == 0 ) // Disable write if someone is taking branch

                case (MEM_WB_type)
                RR_ALU : Reg[MEM_WB_IR[15:11]] <= #2 MEM_WB_ALUout ; 

                RM_ALU : Reg[MEM_WB_IR[20:16]] <= #2 MEM_WB_ALUout ;

                LOAD : Reg[MEM_WB_IR[20:16]] <= #2 MEM_WB_LMD ;

                HALT : HALTED <= #2 1'b1 ;
                endcase 
        end


endmodule

test_1.v
module test_1_MIPS ;

reg clk1,clk2 ;
integer i,j ;

MIPS_32 mips(clk1,clk2) ;

initial                           // Two phase non-overlapping clock
    begin                          
        clk1=1'b0 ;
        clk2=1'b0 ;
        repeat (20)
            begin
                #5 clk1 = 1'b1 ;
                #5 clk1 = 1'b0 ;
                #5 clk2 = 1'b1 ;
                #5 clk2 = 1'b0 ;
            end
    end

initial
    begin
        for (i=0;i<32;i=i+1)                 // INTIALIZING THE REGISTERS
            mips.Reg[i] = i ;

        mips.Mem[0] = 32'h2801000a ;        // INSTRUCTIONS LOADED IN MEMORY
        mips.Mem[1] = 32'h28020014 ;        
        mips.Mem[2] = 32'h28030019 ;        
        mips.Mem[3] = 32'h0ce77800 ;        // dummy instruction [ To avoid DATA HAZARD ]
        mips.Mem[4] = 32'h0ce77800 ;        // dummy instruction [ To avoid DATA HAZARD ]
        mips.Mem[5] = 32'h00222000 ;        
        mips.Mem[6] = 32'h0ce77800 ;        // dummy instruction [ To avoid DATA HAZARD ]
        mips.Mem[7] = 32'h00832800 ;        
        mips.Mem[8] = 32'hfc000000 ;        
    end

initial
    begin
        $dumpfile ("mips_1.vcd") ;
        $dumpvars (0,test_1_MIPS) ;
        mips.HALTED = 0 ;
        mips.PC = 0 ;
        mips.TAKEN_BRANCH = 0 ;

        #280 
        for (j=0;j<6;j=j+1)
            $display ("R%1d = %2d ",j,mips.Reg[j]) ;

        #300 $finish ;    
    end
endmodule

mips_1.vcd
$date
	Sun Jun 15 17:58:41 2025
$end
$version
	Icarus Verilog
$end
$timescale
	1s
$end
$scope module test_1_MIPS $end
$var reg 1 ! clk1 $end
$var reg 1 " clk2 $end
$var integer 32 # i [31:0] $end
$var integer 32 $ j [31:0] $end
$scope module mips $end
$var wire 1 ! clk1 $end
$var wire 1 " clk2 $end
$var wire 5 % rt [4:0] $end
$var wire 5 & rs [4:0] $end
$var wire 6 ' op_code [5:0] $end
$var wire 16 ( immediate [15:0] $end
$var parameter 6 ) ADD $end
$var parameter 6 * ADDI $end
$var parameter 6 + AND $end
$var parameter 6 , BEQZ $end
$var parameter 6 - BNEQZ $end
$var parameter 3 . BRANCH $end
$var parameter 3 / HALT $end
$var parameter 6 0 HLT $end
$var parameter 3 1 LOAD $end
$var parameter 6 2 LW $end
$var parameter 6 3 MUL $end
$var parameter 6 4 OR $end
$var parameter 3 5 RM_ALU $end
$var parameter 3 6 RR_ALU $end
$var parameter 6 7 SLT $end
$var parameter 6 8 SLTI $end
$var parameter 3 9 STORE $end
$var parameter 6 : SUB $end
$var parameter 6 ; SUBI $end
$var parameter 6 < SW $end
$var reg 32 = EX_MEM_ALUout [31:0] $end
$var reg 32 > EX_MEM_B [31:0] $end
$var reg 32 ? EX_MEM_IR [31:0] $end
$var reg 32 @ EX_MEM_cond [31:0] $end
$var reg 3 A EX_MEM_type [2:0] $end
$var reg 1 B HALTED $end
$var reg 32 C ID_EX_A [31:0] $end
$var reg 32 D ID_EX_B [31:0] $end
$var reg 32 E ID_EX_IR [31:0] $end
$var reg 32 F ID_EX_Imm [31:0] $end
$var reg 32 G ID_EX_NPC [31:0] $end
$var reg 3 H ID_EX_type [2:0] $end
$var reg 32 I IF_ID_IR [31:0] $end
$var reg 32 J IF_ID_NPC [31:0] $end
$var reg 32 K MEM_WB_ALUout [31:0] $end
$var reg 32 L MEM_WB_IR [31:0] $end
$var reg 32 M MEM_WB_LMD [31:0] $end
$var reg 3 N MEM_WB_type [2:0] $end
$var reg 32 O PC [31:0] $end
$var reg 1 P TAKEN_BRANCH $end
$upscope $end
$upscope $end
$enddefinitions $end
$comment Show the parameter values. $end
$dumpall
b1001 <
b1011 ;
b1 :
b11 9
b1100 8
b100 7
b0 6
b1 5
b11 4
b101 3
b1000 2
b10 1
b111111 0
b101 /
b100 .
b1101 -
b1110 ,
b10 +
b1010 *
b0 )
$end
#0
$dumpvars
0P
b0 O
bx N
bx M
bx L
bx K
bx J
bx I
bx H
bx G
bx F
bx E
bx D
bx C
0B
bx A
bx @
bx ?
bx >
bx =
bx (
bx '
bx &
bx %
bx $
b100000 #
0"
0!
$end
#5
1!
#7
b1010 '
b0 &
b1 %
b1010 (
b1 O
b1 J
b101000000000010000000000001010 I
#10
0!
#15
1"
#17
b1 G
b101000000000010000000000001010 E
b1010 F
b1 D
b0 C
b1 H
#20
0"
#25
1!
#27
b10 %
b10100 (
b1010 =
b1 A
b101000000000010000000000001010 ?
b10 O
b10 J
b101000000000100000000000010100 I
#30
0!
#35
1"
#37
b1010 K
b1 N
b101000000000010000000000001010 L
b10 G
b101000000000100000000000010100 E
b10100 F
b10 D
#40
0"
#45
1!
#47
b11 %
b11001 (
b11 O
b11 J
b101000000000110000000000011001 I
b10100 =
b101000000000100000000000010100 ?
#50
0!
#55
1"
#57
b11 G
b101000000000110000000000011001 E
b11001 F
b11 D
b10100 K
b101000000000100000000000010100 L
#60
0"
#65
1!
#67
b11 '
b111 &
b111 %
b111100000000000 (
b11001 =
b101000000000110000000000011001 ?
b100 O
b100 J
b1100111001110111100000000000 I
#70
0!
#75
1"
#77
b11001 K
b101000000000110000000000011001 L
b100 G
b1100111001110111100000000000 E
b111100000000000 F
b111 D
b111 C
b0 H
#80
0"
#85
1!
#87
b101 O
b101 J
b111 =
b0 A
b1100111001110111100000000000 ?
#90
0!
#95
1"
#97
b101 G
b111 K
b0 N
b1100111001110111100000000000 L
#100
0"
#105
1!
#107
b0 '
b1 &
b10 %
b10000000000000 (
b110 O
b110 J
b1000100010000000000000 I
#110
0!
#115
1"
#117
b110 G
b1000100010000000000000 E
b10000000000000 F
b10100 D
b1010 C
#120
0"
#125
1!
#127
b11 '
b111 &
b111 %
b111100000000000 (
b111 O
b111 J
b1100111001110111100000000000 I
b11110 =
b1000100010000000000000 ?
#130
0!
#135
1"
#137
b111 G
b1100111001110111100000000000 E
b111100000000000 F
b111 D
b111 C
b11110 K
b1000100010000000000000 L
#140
0"
#145
1!
#147
b0 '
b100 &
b11 %
b10100000000000 (
b111 =
b1100111001110111100000000000 ?
b1000 O
b1000 J
b100000110010100000000000 I
#150
0!
#155
1"
#157
b111 K
b1100111001110111100000000000 L
b1000 G
b100000110010100000000000 E
b10100000000000 F
b11001 D
b11110 C
#160
0"
#165
1!
#167
b111111 '
b0 &
b0 %
b0 (
b1001 O
b1001 J
b11111100000000000000000000000000 I
b110111 =
b100000110010100000000000 ?
#170
0!
#175
1"
#177
b1001 G
b11111100000000000000000000000000 E
b0 F
b0 D
b0 C
b101 H
b110111 K
b100000110010100000000000 L
#180
0"
#185
1!
#187
bx '
bx &
bx %
bx (
b101 A
b11111100000000000000000000000000 ?
b1010 O
b1010 J
bx I
#190
0!
#195
1"
#197
b101 N
b11111100000000000000000000000000 L
b1010 G
bx E
bx F
bx D
bx C
#200
0"
#205
1!
#207
b1011 O
b1011 J
bx ?
1B
#210
0!
#215
1"
#220
0"
#225
1!
#230
0!
#235
1"
#240
0"
#245
1!
#250
0!
#255
1"
#260
0"
#265
1!
#270
0!
#275
1"
#280
0"
b110 $
