MIPS32_RISC.v
// *** MIPS32 PROCESSOR USING 5-STAGE PIPELINING RISC-V 

module MIPS_32 (clk1,clk2) ;

input clk1,clk2 ; // Two phase non-overlapping clock

reg [31:0] PC , IF_ID_IR , IF_ID_NPC ;    // IF_ID pipeline latch
reg [31:0] ID_EX_NPC , ID_EX_A , ID_EX_B , ID_EX_Imm , ID_EX_IR ; // ID_EX pipeline latch
reg [2:0] ID_EX_type , EX_MEM_type , MEM_WB_type ;
reg [31:0] EX_MEM_cond , EX_MEM_ALUout , EX_MEM_B , EX_MEM_IR ; // EX_MEM pipeline latch 
reg [31:0] MEM_WB_LMD , MEM_WB_ALUout , MEM_WB_IR ;  // MEM_WB pipeline latch

reg [31:0] Reg [0:31] ;  // Register Bank [ 32 registers X 32 bits ]
reg [31:0] Mem [0:1023] ; // Memory [ 1024 words X 32 bits ]

parameter ADD=6'b000000 , SUB=6'b000001 , AND=6'b000010 , OR=6'b000011 , SLT=6'b000100 , MUL=6'b000101 , // Arithemetic and Logical Instructions
          HLT=6'b111111 , // Halt Instruction 
          LW=6'b001000 , SW=6'b001001 , // Load and Store Instructions
          ADDI=6'b001010 , SUBI=6'b001011 , SLTI=6'b001100 , // Immediate Instructions
          BNEQZ=6'b001101 , BEQZ=6'b001110 ;  // Branch Instructions

parameter RR_ALU=3'b000 , RM_ALU=3'b001 , LOAD=3'b010 , 
          STORE=3'b011 , BRANCH=3'b100 , HALT=3'b101 ;          
          
reg HALTED ; // Set after HLT instruction is completed ( in WB stage ) 
reg TAKEN_BRANCH ;  // Required to disable instructions after branch

wire [4:0] rs,rt ; // rs --> Source Register 1 (rs <- IR[25:21]) || rt --> Source Register 2 (rt <- IR[20:16])
wire [5:0] op_code ;  // op_code <-- IR[31:26]
wire [15:0] immediate ;  // immediate <-- IR[15:0]

assign op_code = IF_ID_IR[31:26] ;
assign rs = IF_ID_IR[25:21] ;
assign rt = IF_ID_IR[20:16] ;
assign immediate = IF_ID_IR[15:0] ;


// ***** IF STAGE *****
always @ (posedge clk1) 
    
    if ( HALTED==0 )
            begin
                if ( ( (EX_MEM_IR[31:26] == BEQZ) && (EX_MEM_cond == 1) ) || 
                     ( (EX_MEM_IR[31:26] == BNEQZ) && (EX_MEM_cond == 0) ) )   // FOR BRANCH INSTRUCTIONS

                    begin
                        IF_ID_IR <= #2 Mem[EX_MEM_ALUout] ;
                        TAKEN_BRANCH <= #2 1'b1 ;
                        IF_ID_NPC <= #2 EX_MEM_ALUout ;
                        PC <= #2 EX_MEM_ALUout ;
                    end

                else
                    begin                            // FOR NORMAL ARITHMETIC AND LOGIC INSTRUCTIONS
                        IF_ID_IR <= #2 Mem[PC] ;
                        IF_ID_NPC <= #2 PC+1 ;
                        PC <= #2 PC+1 ;
                    end    

            end

// ***** ID STAGE ***** 
always @ (posedge clk2)

    if (HALTED==0)
        begin
            case (op_code)   // Operation_Code
                ADD,SUB,MUL,AND,OR,SLT : ID_EX_type <= #2 RR_ALU ;
                ADDI,SUBI,SLTI : ID_EX_type <= #2 RM_ALU ;
                LW : ID_EX_type <= #2 LOAD ;
                SW : ID_EX_type <= #2 STORE ;
                BNEQZ,BEQZ : ID_EX_type <= #2 BRANCH ;
                HLT : ID_EX_type <= #2 HALT ;

                default : ID_EX_type <= #2 HALT ; // invalid op_code
            endcase

            if ( rs == 5'b00000 ) ID_EX_A <= #2 0 ;
            else ID_EX_A <= #2 Reg[rs] ;   // Source Register 1

            if ( rt == 5'b00000 ) ID_EX_B <= #2 0 ;
            else ID_EX_B <= #2 Reg[rt] ;   // Source Register 2

            ID_EX_Imm <= #2 {{16{immediate[15]}}, immediate} ;  // Sign extension

            ID_EX_IR <= #2 IF_ID_IR ;
            ID_EX_NPC <= #2 IF_ID_NPC ;
        end

// ***** EX STAGE *****
always @ (posedge clk1)

    if ( HALTED==0 )
        begin
            EX_MEM_IR <= #2 ID_EX_IR ;
            EX_MEM_type <= #2 ID_EX_type ;
            TAKEN_BRANCH <= #2 1'b0 ; // Reset the "TAKEN_BRANCH"

            case (ID_EX_type)

            RR_ALU : begin  
                        case (ID_EX_IR[31:26])  // opcode
                        ADD : EX_MEM_ALUout <= #2 ID_EX_A + ID_EX_B ;
                        SUB : EX_MEM_ALUout <= #2 ID_EX_A - ID_EX_B ;
                        MUL : EX_MEM_ALUout <= #2 ID_EX_A * ID_EX_B ;
                        AND : EX_MEM_ALUout <= #2 ID_EX_A & ID_EX_B ;
                        OR  : EX_MEM_ALUout <= #2 ID_EX_A | ID_EX_B ;
                        SLT : EX_MEM_ALUout <= #2 ID_EX_A < ID_EX_B ;
                        default :EX_MEM_ALUout <= #2 32'hxxxxxxxx ;
                        endcase
                     end

            RM_ALU : begin 
                        case (ID_EX_IR[31:26]) // opcode
                        ADDI : EX_MEM_ALUout <= #2 ID_EX_A + ID_EX_Imm ;
                        SUBI : EX_MEM_ALUout <= #2 ID_EX_A - ID_EX_Imm ;
                        SLTI : EX_MEM_ALUout <= #2 ID_EX_A < ID_EX_Imm ;
                        default :EX_MEM_ALUout <= #2 32'hxxxxxxxx ;
                        endcase
                     end     

            LOAD,STORE :begin   
                            EX_MEM_ALUout <= #2 ID_EX_A + ID_EX_Imm ;
                            EX_MEM_B <= #2 ID_EX_B ;   // required for store instructions
                        end       

            BRANCH : begin
                        EX_MEM_ALUout <= #2 ID_EX_NPC + ID_EX_Imm ;
                        EX_MEM_cond <= #2 (ID_EX_A == 0) ;
                     end         

            endcase 
        end

// ***** MEM STAGE *****
always @ (posedge clk2)

    if ( HALTED == 0 )
        begin
            MEM_WB_IR <= #2 EX_MEM_IR ;
            MEM_WB_type <= #2 EX_MEM_type ;

            case (EX_MEM_type)
            RR_ALU,RM_ALU : MEM_WB_ALUout <= #2 EX_MEM_ALUout ;

            LOAD : MEM_WB_LMD <= #2 Mem[EX_MEM_ALUout] ;

            STORE : if ( TAKEN_BRANCH == 0 )
                        Mem[EX_MEM_ALUout] <= #2 EX_MEM_B ;
            endcase
        end

// ***** WB STAGE *****
always @(posedge clk1)

        begin
            if ( TAKEN_BRANCH == 0 ) // Disable write if someone is taking branch

                case (MEM_WB_type)
                RR_ALU : Reg[MEM_WB_IR[15:11]] <= #2 MEM_WB_ALUout ; 

                RM_ALU : Reg[MEM_WB_IR[20:16]] <= #2 MEM_WB_ALUout ;

                LOAD : Reg[MEM_WB_IR[20:16]] <= #2 MEM_WB_LMD ;

                HALT : HALTED <= #2 1'b1 ;
                endcase 
        end


endmodule

test_3.v
module test_3_MIPS ;

reg clk1,clk2 ;
integer i,j ;

MIPS_32 mips(clk1,clk2) ;

initial                           // Two phase non-overlapping clock
    begin                          
        clk1=1'b0 ;
        clk2=1'b0 ;
        repeat (20)
            begin
                #5 clk1 = 1'b1 ;
                #5 clk1 = 1'b0 ;
                #5 clk2 = 1'b1 ;
                #5 clk2 = 1'b0 ;
            end
    end

initial
    begin
        for (i=0;i<32;i=i+1)                 // INTIALIZING THE REGISTERS
            mips.Reg[i] = i ;

        mips.Mem[0] = 32'h280a00c8 ;        // INSTRUCTIONS LOADED IN MEMORY
        mips.Mem[1] = 32'h28020001 ;        
        mips.Mem[2] = 32'h0e94a000 ;       // dummy instruction [ To avoid DATA HAZARD ]
        mips.Mem[3] = 32'h21430000 ;        
        mips.Mem[4] = 32'h0e94a000 ;       // dummy instruction [ To avoid DATA HAZARD ]
        mips.Mem[5] = 32'h14431000 ;       
        mips.Mem[6] = 32'h2c630001 ;        
        mips.Mem[7] = 32'h0e94a000 ;       // dummy instruction [ To avoid DATA HAZARD ]
        mips.Mem[8] = 32'h3460fffc ;       
        mips.Mem[9] = 32'h2542fffe ;       
        mips.Mem[10] = 32'hfc000000 ;       

        mips.Mem[200] = 32'd7 ;        
    end

initial
    begin
        $dumpfile ("mips_3.vcd") ;
        $dumpvars (0,test_3_MIPS) ;
        $monitor ("R2 = %4d",mips.Reg[2]) ;

        mips.HALTED = 0 ;
        mips.PC = 0 ;
        mips.TAKEN_BRANCH = 0 ;

        #4000 
        $display ("Mem[200] = %2d | Mem[198] =%6d ",mips.Mem[200],mips.Mem[198]) ;

        #3000 $finish ;    
    end
endmodule

mips_3.vcd
$date
	Mon Jun 16 00:07:47 2025
$end
$version
	Icarus Verilog
$end
$timescale
	1s
$end
$scope module test_3_MIPS $end
$var reg 1 ! clk1 $end
$var reg 1 " clk2 $end
$var integer 32 # i [31:0] $end
$scope module mips $end
$var wire 1 ! clk1 $end
$var wire 1 " clk2 $end
$var wire 5 $ rt [4:0] $end
$var wire 5 % rs [4:0] $end
$var wire 6 & op_code [5:0] $end
$var wire 16 ' immediate [15:0] $end
$var parameter 6 ( ADD $end
$var parameter 6 ) ADDI $end
$var parameter 6 * AND $end
$var parameter 6 + BEQZ $end
$var parameter 6 , BNEQZ $end
$var parameter 3 - BRANCH $end
$var parameter 3 . HALT $end
$var parameter 6 / HLT $end
$var parameter 3 0 LOAD $end
$var parameter 6 1 LW $end
$var parameter 6 2 MUL $end
$var parameter 6 3 OR $end
$var parameter 3 4 RM_ALU $end
$var parameter 3 5 RR_ALU $end
$var parameter 6 6 SLT $end
$var parameter 6 7 SLTI $end
$var parameter 3 8 STORE $end
$var parameter 6 9 SUB $end
$var parameter 6 : SUBI $end
$var parameter 6 ; SW $end
$var reg 32 < EX_MEM_ALUout [31:0] $end
$var reg 32 = EX_MEM_B [31:0] $end
$var reg 32 > EX_MEM_IR [31:0] $end
$var reg 32 ? EX_MEM_cond [31:0] $end
$var reg 3 @ EX_MEM_type [2:0] $end
$var reg 1 A HALTED $end
$var reg 32 B ID_EX_A [31:0] $end
$var reg 32 C ID_EX_B [31:0] $end
$var reg 32 D ID_EX_IR [31:0] $end
$var reg 32 E ID_EX_Imm [31:0] $end
$var reg 32 F ID_EX_NPC [31:0] $end
$var reg 3 G ID_EX_type [2:0] $end
$var reg 32 H IF_ID_IR [31:0] $end
$var reg 32 I IF_ID_NPC [31:0] $end
$var reg 32 J MEM_WB_ALUout [31:0] $end
$var reg 32 K MEM_WB_IR [31:0] $end
$var reg 32 L MEM_WB_LMD [31:0] $end
$var reg 3 M MEM_WB_type [2:0] $end
$var reg 32 N PC [31:0] $end
$var reg 1 O TAKEN_BRANCH $end
$upscope $end
$upscope $end
$enddefinitions $end
$comment Show the parameter values. $end
$dumpall
b1001 ;
b1011 :
b1 9
b11 8
b1100 7
b100 6
b0 5
b1 4
b11 3
b101 2
b1000 1
b10 0
b111111 /
b101 .
b100 -
b1101 ,
b1110 +
b10 *
b1010 )
b0 (
$end
#0
$dumpvars
0O
b0 N
bx M
bx L
bx K
bx J
bx I
bx H
bx G
bx F
bx E
bx D
bx C
bx B
0A
bx @
bx ?
bx >
bx =
bx <
bx '
bx &
bx %
bx $
b100000 #
0"
0!
$end
#5
1!
#7
b1010 &
b0 %
b1010 $
b11001000 '
b1 N
b1 I
b101000000010100000000011001000 H
#10
0!
#15
1"
#17
b1 F
b101000000010100000000011001000 D
b11001000 E
b1010 C
b0 B
b1 G
#20
0"
#25
1!
#27
b10 $
b1 '
b11001000 <
b1 @
b101000000010100000000011001000 >
b10 N
b10 I
b101000000000100000000000000001 H
#30
0!
#35
1"
#37
b11001000 J
b1 M
b101000000010100000000011001000 K
b10 F
b101000000000100000000000000001 D
b1 E
b10 C
#40
0"
#45
1!
#47
b11 &
b10100 %
b10100 $
b1010000000000000 '
b11 N
b11 I
b1110100101001010000000000000 H
b1 <
b101000000000100000000000000001 >
#50
0!
#55
1"
#57
b11 F
b1110100101001010000000000000 D
b11111111111111111010000000000000 E
b10100 C
b10100 B
b0 G
b1 J
b101000000000100000000000000001 K
#60
0"
#65
1!
#67
b1000 &
b1010 %
b11 $
b0 '
b10100 <
b0 @
b1110100101001010000000000000 >
b100 N
b100 I
b100001010000110000000000000000 H
#70
0!
#75
1"
#77
b10100 J
b0 M
b1110100101001010000000000000 K
b100 F
b100001010000110000000000000000 D
b0 E
b11 C
b11001000 B
b10 G
#80
0"
#85
1!
#87
b11 &
b10100 %
b10100 $
b1010000000000000 '
b101 N
b101 I
b1110100101001010000000000000 H
b11 =
b11001000 <
b10 @
b100001010000110000000000000000 >
#90
0!
#95
1"
#97
b101 F
b1110100101001010000000000000 D
b11111111111111111010000000000000 E
b10100 C
b10100 B
b0 G
b111 L
b10 M
b100001010000110000000000000000 K
#100
0"
#105
1!
#107
b101 &
b10 %
b11 $
b1000000000000 '
b10100 <
b0 @
b1110100101001010000000000000 >
b110 N
b110 I
b10100010000110001000000000000 H
#110
0!
#115
1"
#117
b0 M
b1110100101001010000000000000 K
b110 F
b10100010000110001000000000000 D
b1000000000000 E
b111 C
b1 B
#120
0"
#125
1!
#127
b1011 &
b11 %
b1 '
b111 N
b111 I
b101100011000110000000000000001 H
b111 <
b10100010000110001000000000000 >
#130
0!
#135
1"
#137
b111 F
b101100011000110000000000000001 D
b1 E
b111 B
b1 G
b111 J
b10100010000110001000000000000 K
#140
0"
#145
1!
#147
b11 &
b10100 %
b10100 $
b1010000000000000 '
b110 <
b1 @
b101100011000110000000000000001 >
b1000 N
b1000 I
b1110100101001010000000000000 H
#150
0!
#155
1"
#157
b110 J
b1 M
b101100011000110000000000000001 K
b1000 F
b1110100101001010000000000000 D
b11111111111111111010000000000000 E
b10100 C
b10100 B
b0 G
#160
0"
#165
1!
#167
b1101 &
b11 %
b0 $
b1111111111111100 '
b1001 N
b1001 I
b110100011000001111111111111100 H
b10100 <
b0 @
b1110100101001010000000000000 >
#170
0!
#175
1"
#177
b1001 F
b110100011000001111111111111100 D
b11111111111111111111111111111100 E
b0 C
b110 B
b100 G
b10100 J
b0 M
b1110100101001010000000000000 K
#180
0"
#185
1!
#187
b1001 &
b1010 %
b10 $
b1111111111111110 '
b0 ?
b101 <
b100 @
b110100011000001111111111111100 >
b1010 N
b1010 I
b100101010000101111111111111110 H
#190
0!
#195
1"
#197
b100 M
b110100011000001111111111111100 K
b1010 F
b100101010000101111111111111110 D
b11111111111111111111111111111110 E
b111 C
b11001000 B
b11 G
#200
0"
#205
1!
#207
b101 &
b10 %
b11 $
b1000000000000 '
b101 N
b101 I
1O
b10100010000110001000000000000 H
b111 =
b11000110 <
b11 @
b100101010000101111111111111110 >
#210
0!
#215
1"
#217
b101 F
b10100010000110001000000000000 D
b1000000000000 E
b110 C
b111 B
b0 G
b11 M
b100101010000101111111111111110 K
#220
0"
#225
1!
#227
b101010 <
0O
b0 @
b10100010000110001000000000000 >
b110 N
b110 I
#230
0!
#235
1"
#237
b101010 J
b0 M
b10100010000110001000000000000 K
b110 F
#240
0"
#245
1!
#247
b1011 &
b11 %
b1 '
b111 N
b111 I
b101100011000110000000000000001 H
#250
0!
#255
1"
#257
b111 F
b101100011000110000000000000001 D
b1 E
b110 B
b1 G
#260
0"
#265
1!
#267
b11 &
b10100 %
b10100 $
b1010000000000000 '
b101 <
b1 @
b101100011000110000000000000001 >
b1000 N
b1000 I
b1110100101001010000000000000 H
#270
0!
#275
1"
#277
b101 J
b1 M
b101100011000110000000000000001 K
b1000 F
b1110100101001010000000000000 D
b11111111111111111010000000000000 E
b10100 C
b10100 B
b0 G
#280
0"
#285
1!
#287
b1101 &
b11 %
b0 $
b1111111111111100 '
b1001 N
b1001 I
b110100011000001111111111111100 H
b10100 <
b0 @
b1110100101001010000000000000 >
#290
0!
#295
1"
#297
b1001 F
b110100011000001111111111111100 D
b11111111111111111111111111111100 E
b0 C
b101 B
b100 G
b10100 J
b0 M
b1110100101001010000000000000 K
#300
0"
#305
1!
#307
b1001 &
b1010 %
b10 $
b1111111111111110 '
b101 <
b100 @
b110100011000001111111111111100 >
b1010 N
b1010 I
b100101010000101111111111111110 H
#310
0!
#315
1"
#317
b100 M
b110100011000001111111111111100 K
b1010 F
b100101010000101111111111111110 D
b11111111111111111111111111111110 E
b101010 C
b11001000 B
b11 G
#320
0"
#325
1!
#327
b101 &
b10 %
b11 $
b1000000000000 '
b101 N
b101 I
1O
b10100010000110001000000000000 H
b101010 =
b11000110 <
b11 @
b100101010000101111111111111110 >
#330
0!
#335
1"
#337
b101 F
b10100010000110001000000000000 D
b1000000000000 E
b101 C
b101010 B
b0 G
b11 M
b100101010000101111111111111110 K
#340
0"
#345
1!
#347
b11010010 <
0O
b0 @
b10100010000110001000000000000 >
b110 N
b110 I
#350
0!
#355
1"
#357
b11010010 J
b0 M
b10100010000110001000000000000 K
b110 F
#360
0"
#365
1!
#367
b1011 &
b11 %
b1 '
b111 N
b111 I
b101100011000110000000000000001 H
#370
0!
#375
1"
#377
b111 F
b101100011000110000000000000001 D
b1 E
b101 B
b1 G
#380
0"
#385
1!
#387
b11 &
b10100 %
b10100 $
b1010000000000000 '
b100 <
b1 @
b101100011000110000000000000001 >
b1000 N
b1000 I
b1110100101001010000000000000 H
#390
0!
#395
1"
#397
b100 J
b1 M
b101100011000110000000000000001 K
b1000 F
b1110100101001010000000000000 D
b11111111111111111010000000000000 E
b10100 C
b10100 B
b0 G
